Workbook

Sheet CALENDARIO
B33: FASES | N33: FASES
C35: FECHA TENTATIVA DE REVISION | D35: FASE | E35: ACTIVIDADES PARA REVISAR CON CHECKLIST | F35: ESTADO | G35: total | H35: items hechas | I35: items sin hacer | J35: AAR | K35: LLG | L35: MTR | M35: EGB | N35: SMR | O35: EVIDENCIA | P35: CONTENIDO
C36: 46204 | D36: 1 Planeación | E36: Definir pregunta de investigación, objetivos, criterios de inclusión/exclusión y equipo de trabajo. | F36: =_xlfn.PERCENTOF(H36,G36) -> 0.93333333 | G36: =COUNTIF(Checklist!$A:$A,TEXT(CALENDARIO!D36,1)) -> 15 | H36: =G36-I36 -> 14 | I36: =COUNTIFS(Checklist!$A:$A,TEXT(CALENDARIO!D36,1),Checklist!$J:$J,0) -> 1 | J36: =_xlfn.PERCENTOF(COUNTIFS(Checklist!$A:$A,TEXT(CALENDARIO!D36,1),Checklist!$E:$E,TRUE),G36) -> 0.53333333 | K36: =_xlfn.PERCENTOF(COUNTIFS(Checklist!$A:$A,TEXT(CALENDARIO!D36,1),Checklist!$F:$F,TRUE),G36) -> 0.13333333 | L36: =_xlfn.PERCENTOF(COUNTIFS(Checklist!$A:$A,TEXT(CALENDARIO!D36,1),Checklist!$G:$G,TRUE),G36) -> 0.46666667 | M36: =_xlfn.PERCENTOF(COUNTIFS(Checklist!$A:$A,TEXT(CALENDARIO!D36,1),Checklist!$H:$H,TRUE),G36) -> 0 | N36: =_xlfn.PERCENTOF(COUNTIFS(Checklist!$A:$A,TEXT(CALENDARIO!D36,1),Checklist!$I:$I,TRUE),G36) -> 0.33333333 | O36: PROTOCOLO FIRMADO | P36: PROTOCOLO COORDINACION
C37: 46245 | D37: 2 Protocolo | E37: Redactar el protocolo y registrar la revisión si aplica. | F37: =_xlfn.PERCENTOF(H37,G37) -> 1 | G37: =COUNTIF(Checklist!$A:$A,TEXT(CALENDARIO!D37,1)) -> 20 | H37: =G37-I37 -> 20 | I37: =COUNTIFS(Checklist!$A:$A,TEXT(CALENDARIO!D37,1),Checklist!$J:$J,0) -> 0 | J37: =_xlfn.PERCENTOF(COUNTIFS(Checklist!$A:$A,TEXT(CALENDARIO!D37,1),Checklist!$E:$E,TRUE),G37) -> 0.7 | K37: =_xlfn.PERCENTOF(COUNTIFS(Checklist!$A:$A,TEXT(CALENDARIO!D37,1),Checklist!$F:$F,TRUE),G37) -> 0.1 | L37: =_xlfn.PERCENTOF(COUNTIFS(Checklist!$A:$A,TEXT(CALENDARIO!D37,1),Checklist!$G:$G,TRUE),G37) -> 0.9 | M37: =_xlfn.PERCENTOF(COUNTIFS(Checklist!$A:$A,TEXT(CALENDARIO!D37,1),Checklist!$H:$H,TRUE),G37) -> 0 | N37: =_xlfn.PERCENTOF(COUNTIFS(Checklist!$A:$A,TEXT(CALENDARIO!D37,1),Checklist!$I:$I,TRUE),G37) -> 0.1 | O37: C:\Users\estef\OneDrive\PROTOCOL 2.0.pdf | P37: PROTOCOLO EN PROSPERO | Q37: TÍTULO
C38: 46266 | D38: 3 Estrategia de búsqueda | E38: Diseñar ecuaciones de búsqueda, seleccionar bases de datos y probar la estrategia. | F38: =_xlfn.PERCENTOF(H38,G38) -> 0.98148148 | G38: =COUNTIF(Checklist!$A:$A,TEXT(CALENDARIO!D38,1)) -> 54 | H38: =G38-I38 -> 53 | I38: =COUNTIFS(Checklist!$A:$A,TEXT(CALENDARIO!D38,1),Checklist!$J:$J,0) -> 1 | J38: =_xlfn.PERCENTOF(COUNTIFS(Checklist!$A:$A,TEXT(CALENDARIO!D38,1),Checklist!$E:$E,TRUE),G38) -> 0.96296296 | K38: =_xlfn.PERCENTOF(COUNTIFS(Checklist!$A:$A,TEXT(CALENDARIO!D38,1),Checklist!$F:$F,TRUE),G38) -> 0 | L38: =_xlfn.PERCENTOF(COUNTIFS(Checklist!$A:$A,TEXT(CALENDARIO!D38,1),Checklist!$G:$G,TRUE),G38) -> 0.037037037 | M38: =_xlfn.PERCENTOF(COUNTIFS(Checklist!$A:$A,TEXT(CALENDARIO!D38,1),Checklist!$H:$H,TRUE),G38) -> 0 | N38: =_xlfn.PERCENTOF(COUNTIFS(Checklist!$A:$A,TEXT(CALENDARIO!D38,1),Checklist!$I:$I,TRUE),G38) -> 0 | P38: ANEXO ESTRATEGIAS | Q38: ARCHIVOS
C39: 46270 | D39: 4 Búsqueda bibliográfica | E39: Ejecutar búsquedas en bases de datos y otras fuentes, descargar resultados y eliminar duplicados. | F39: =_xlfn.PERCENTOF(H39,G39) -> 1 | G39: =COUNTIF(Checklist!$A:$A,TEXT(CALENDARIO!D39,1)) -> 2 | H39: =G39-I39 -> 2 | I39: =COUNTIFS(Checklist!$A:$A,TEXT(CALENDARIO!D39,1),Checklist!$J:$J,0) -> 0 | J39: =_xlfn.PERCENTOF(COUNTIFS(Checklist!$A:$A,TEXT(CALENDARIO!D39,1),Checklist!$E:$E,TRUE),G39) -> 1 | K39: =_xlfn.PERCENTOF(COUNTIFS(Checklist!$A:$A,TEXT(CALENDARIO!D39,1),Checklist!$F:$F,TRUE),G39) -> 1 | L39: =_xlfn.PERCENTOF(COUNTIFS(Checklist!$A:$A,TEXT(CALENDARIO!D39,1),Checklist!$G:$G,TRUE),G39) -> 0 | M39: =_xlfn.PERCENTOF(COUNTIFS(Checklist!$A:$A,TEXT(CALENDARIO!D39,1),Checklist!$H:$H,TRUE),G39) -> 0 | N39: =_xlfn.PERCENTOF(COUNTIFS(Checklist!$A:$A,TEXT(CALENDARIO!D39,1),Checklist!$I:$I,TRUE),G39) -> 0 | P39: MÉTODOS AVANCE | Q39: INTRODUCCIÓN AVANCE
C40: 46280 | D40: 5 Selección de estudios | E40: Revisar títulos/resúmenes y luego textos completos según criterios de elegibilidad. | F40: =_xlfn.PERCENTOF(H40,G40) -> 0 | G40: =COUNTIF(Checklist!$A:$A,TEXT(CALENDARIO!D40,1)) -> 1 | H40: =G40-I40 -> 0 | I40: =COUNTIFS(Checklist!$A:$A,TEXT(CALENDARIO!D40,1),Checklist!$J:$J,0) -> 1 | J40: =_xlfn.PERCENTOF(COUNTIFS(Checklist!$A:$A,TEXT(CALENDARIO!D40,1),Checklist!$E:$E,TRUE),G40) -> 0 | K40: =_xlfn.PERCENTOF(COUNTIFS(Checklist!$A:$A,TEXT(CALENDARIO!D40,1),Checklist!$F:$F,TRUE),G40) -> 0 | L40: =_xlfn.PERCENTOF(COUNTIFS(Checklist!$A:$A,TEXT(CALENDARIO!D40,1),Checklist!$G:$G,TRUE),G40) -> 0 | M40: =_xlfn.PERCENTOF(COUNTIFS(Checklist!$A:$A,TEXT(CALENDARIO!D40,1),Checklist!$H:$H,TRUE),G40) -> 0 | N40: =_xlfn.PERCENTOF(COUNTIFS(Checklist!$A:$A,TEXT(CALENDARIO!D40,1),Checklist!$I:$I,TRUE),G40) -> 0
C41: 46295 | D41: 6 Extracción de datos | E41: Diseñar formulario, extraer datos y verificar consistencia entre revisores. | F41: =_xlfn.PERCENTOF(H41,G41) -> 0 | G41: =COUNTIF(Checklist!$A:$A,TEXT(CALENDARIO!D41,1)) -> 2 | H41: =G41-I41 -> 0 | I41: =COUNTIFS(Checklist!$A:$A,TEXT(CALENDARIO!D41,1),Checklist!$J:$J,0) -> 2 | J41: =_xlfn.PERCENTOF(COUNTIFS(Checklist!$A:$A,TEXT(CALENDARIO!D41,1),Checklist!$E:$E,TRUE),G41) -> 0 | K41: =_xlfn.PERCENTOF(COUNTIFS(Checklist!$A:$A,TEXT(CALENDARIO!D41,1),Checklist!$F:$F,TRUE),G41) -> 0 | L41: =_xlfn.PERCENTOF(COUNTIFS(Checklist!$A:$A,TEXT(CALENDARIO!D41,1),Checklist!$G:$G,TRUE),G41) -> 0 | M41: =_xlfn.PERCENTOF(COUNTIFS(Checklist!$A:$A,TEXT(CALENDARIO!D41,1),Checklist!$H:$H,TRUE),G41) -> 0 | N41: =_xlfn.PERCENTOF(COUNTIFS(Checklist!$A:$A,TEXT(CALENDARIO!D41,1),Checklist!$I:$I,TRUE),G41) -> 0 | P41: DIAGRAMA DE FLUJO PRISMA 2020
C42: 46310 | D42: 7 Evaluación de calidad | E42: Valorar riesgo de sesgo o calidad metodológica de los estudios incluidos. | F42: =_xlfn.PERCENTOF(H42,G42) -> 0 | G42: =COUNTIF(Checklist!$A:$A,TEXT(CALENDARIO!D42,1)) -> 8 | H42: =G42-I42 -> 0 | I42: =COUNTIFS(Checklist!$A:$A,TEXT(CALENDARIO!D42,1),Checklist!$J:$J,0) -> 8 | J42: =_xlfn.PERCENTOF(COUNTIFS(Checklist!$A:$A,TEXT(CALENDARIO!D42,1),Checklist!$E:$E,TRUE),G42) -> 0 | K42: =_xlfn.PERCENTOF(COUNTIFS(Checklist!$A:$A,TEXT(CALENDARIO!D42,1),Checklist!$F:$F,TRUE),G42) -> 0 | L42: =_xlfn.PERCENTOF(COUNTIFS(Checklist!$A:$A,TEXT(CALENDARIO!D42,1),Checklist!$G:$G,TRUE),G42) -> 0 | M42: =_xlfn.PERCENTOF(COUNTIFS(Checklist!$A:$A,TEXT(CALENDARIO!D42,1),Checklist!$H:$H,TRUE),G42) -> 0 | N42: =_xlfn.PERCENTOF(COUNTIFS(Checklist!$A:$A,TEXT(CALENDARIO!D42,1),Checklist!$I:$I,TRUE),G42) -> 0 | P42: METODOLOGIA | Q42: .
C43: 46325 | D43: 8 Síntesis | E43: Realizar síntesis narrativa Y meta-análisis, según corresponda. | F43: =_xlfn.PERCENTOF(H43,G43) -> 0 | G43: =COUNTIF(Checklist!$A:$A,TEXT(CALENDARIO!D43,1)) -> 18 | H43: =G43-I43 -> 0 | I43: =COUNTIFS(Checklist!$A:$A,TEXT(CALENDARIO!D43,1),Checklist!$J:$J,0) -> 18 | J43: =_xlfn.PERCENTOF(COUNTIFS(Checklist!$A:$A,TEXT(CALENDARIO!D43,1),Checklist!$E:$E,TRUE),G43) -> 0 | K43: =_xlfn.PERCENTOF(COUNTIFS(Checklist!$A:$A,TEXT(CALENDARIO!D43,1),Checklist!$F:$F,TRUE),G43) -> 0 | L43: =_xlfn.PERCENTOF(COUNTIFS(Checklist!$A:$A,TEXT(CALENDARIO!D43,1),Checklist!$G:$G,TRUE),G43) -> 0 | M43: =_xlfn.PERCENTOF(COUNTIFS(Checklist!$A:$A,TEXT(CALENDARIO!D43,1),Checklist!$H:$H,TRUE),G43) -> 0 | N43: =_xlfn.PERCENTOF(COUNTIFS(Checklist!$A:$A,TEXT(CALENDARIO!D43,1),Checklist!$I:$I,TRUE),G43) -> 0 | P43: RESULTADOS
C44: 46341 | D44: 9 Redacción | E44: Escribir resultados, discusión, conclusiones y preparar figuras/tablas. | F44: =_xlfn.PERCENTOF(H44,G44) -> 0 | G44: =COUNTIF(Checklist!$A:$A,TEXT(CALENDARIO!D44,1)) -> 12 | H44: =G44-I44 -> 0 | I44: =COUNTIFS(Checklist!$A:$A,TEXT(CALENDARIO!D44,1),Checklist!$J:$J,0) -> 12 | J44: =_xlfn.PERCENTOF(COUNTIFS(Checklist!$A:$A,TEXT(CALENDARIO!D44,1),Checklist!$E:$E,TRUE),G44) -> 0 | K44: =_xlfn.PERCENTOF(COUNTIFS(Checklist!$A:$A,TEXT(CALENDARIO!D44,1),Checklist!$F:$F,TRUE),G44) -> 0 | L44: =_xlfn.PERCENTOF(COUNTIFS(Checklist!$A:$A,TEXT(CALENDARIO!D44,1),Checklist!$G:$G,TRUE),G44) -> 0 | M44: =_xlfn.PERCENTOF(COUNTIFS(Checklist!$A:$A,TEXT(CALENDARIO!D44,1),Checklist!$H:$H,TRUE),G44) -> 0 | N44: =_xlfn.PERCENTOF(COUNTIFS(Checklist!$A:$A,TEXT(CALENDARIO!D44,1),Checklist!$I:$I,TRUE),G44) -> 0 | P44: DISCUSIÓN | Q44: FINANCIAMIENTO
C45: 46356 | D45: 10 Revisión final | E45: Correcciones de coautores, ajuste al formato de revista y envío. | F45: =_xlfn.PERCENTOF(H45,G45) -> 0 | G45: =COUNTIF(Checklist!$A:$A,TEXT(CALENDARIO!D45,1)) -> 2 | H45: =G45-I45 -> 0 | I45: =COUNTIFS(Checklist!$A:$A,TEXT(CALENDARIO!D45,1),Checklist!$J:$J,0) -> 2 | J45: =_xlfn.PERCENTOF(COUNTIFS(Checklist!$A:$A,TEXT(CALENDARIO!D45,1),Checklist!$E:$E,TRUE),G45) -> 0 | K45: =_xlfn.PERCENTOF(COUNTIFS(Checklist!$A:$A,TEXT(CALENDARIO!D45,1),Checklist!$F:$F,TRUE),G45) -> 0 | L45: =_xlfn.PERCENTOF(COUNTIFS(Checklist!$A:$A,TEXT(CALENDARIO!D45,1),Checklist!$G:$G,TRUE),G45) -> 0 | M45: =_xlfn.PERCENTOF(COUNTIFS(Checklist!$A:$A,TEXT(CALENDARIO!D45,1),Checklist!$H:$H,TRUE),G45) -> 0 | N45: =_xlfn.PERCENTOF(COUNTIFS(Checklist!$A:$A,TEXT(CALENDARIO!D45,1),Checklist!$I:$I,TRUE),G45) -> 0 | P45: RESUMEN
F46: =_xlfn.PERCENTOF(H46,G46) -> 0.6641791 | G46: =SUM(G36:G45) -> 134 | H46: =SUM(H36:H45) -> 89 | I46: =SUM(I36:I45) -> 45 | J46: =_xlfn.PERCENTOF(J36:J45,$G46) -> 0.023852957 | K46: =_xlfn.PERCENTOF(K36:K45,$G46) -> 0.0092039801 | L46: =_xlfn.PERCENTOF(L36:L45,$G46) -> 0.010475401 | M46: =_xlfn.PERCENTOF(M36:M45,$G46) -> 0 | N46: =_xlfn.PERCENTOF(N36:N45,$G46) -> 0.0032338308

Sheet Hoja2
A3: Cuenta de STATUS | B3: Etiquetas de columna
A4: Etiquetas de fila | B4: 0 | C4: 1 | D4: X | E4: Total general
A5: 1 Planeación | B5: 13 | C5: 2 | E5: 15
A6: 10 Revisión final | B6: 2 | E6: 2
A7: 2 Protocolo | B7: 25 | E7: 25
A8: 3 Estrategia de búsqueda | B8: 54 | E8: 54
A9: 4 Búsqueda bibliográfica | B9: 2 | E9: 2
A10: 5 Selección de estudios | B10: 1 | E10: 1
A11: 6 Extracción de datos | B11: 2 | E11: 2
A12: 7 Evaluación de calidad | B12: 8 | E12: 8
A13: 8 Síntesis | B13: 18 | E13: 18
A14: 9 Redacción | B14: 10 | E14: 10
A15: (en blanco) | D15: 17 | E15: 17
A16: Total general | B16: 135 | C16: 2 | D16: 17 | E16: 154

Sheet Checklist
A1: FASE | B1: Sección/tema | C1: ítem # | D1: ASPECTO A REVISAR | E1: AAR | F1: LLG | G1: MTR | H1: EGB | I1: SMR | J1: STATUS | K1: NOTAS
C2: TITLE | D2: .Tabla 2.- PRISMA 2020 Lista de verificación | J2: X
A3: 2 Protocolo | B3: Titulo | C3: 1 | D3: Identificar la publicación como revisión sistemática, | E3: TRUE | F3: TRUE | G3: FALSE | H3: FALSE | I3: FALSE | J3: =COUNTIF(E3:I3,(NOT(FALSE))) -> 2
C4: RESUMEN | J4: X
A5: 9 Redacción | B5: Resumen | C5: 2 | D5: Consulte la lista de comprobación PRISMA 2020 para resúmenes (Tabla 2). | E5: FALSE | F5: FALSE | G5: FALSE | H5: FALSE | I5: FALSE | J5: =COUNTIF(E5:I5,(NOT(FALSE))) -> 0
C6: INTRODUCTION | J6: X
A7: 9 Redacción | B7: Justificación | C7: 3 | D7: Describa la justificación de la revisión en el contexto de los conocimientos existentes. | E7: FALSE | F7: FALSE | G7: FALSE | H7: FALSE | I7: FALSE | J7: =COUNTIF(E7:I7,(NOT(FALSE))) -> 0
A8: 9 Redacción | B8: Objetivos | C8: 4 | D8: Proporcione una declaración explícita de los objetivos o preguntas que la revisión desea contestar. | E8: FALSE | F8: FALSE | G8: FALSE | H8: FALSE | I8: FALSE | J8: =COUNTIF(E8:I8,(NOT(FALSE))) -> 0
C9: METODOS | J9: X
A10: 3 Estrategia de búsqueda | B10: Criterios de elegibilidad | C10: 5 | D10: Especifique los criterios de inclusión y exclusión para la revisión y cómo se agruparon los estudios para la síntesis. | E10: TRUE | F10: FALSE | G10: FALSE | H10: FALSE | I10: FALSE | J10: =COUNTIF(E10:I10,(NOT(FALSE))) -> 1
A11: 4 Búsqueda bibliográfica | B11: Fuentes de información | C11: 6 | D11: Especifique todas las bases de datos, registros, sitios web, organizaciones, listas de referencia y otras fuentes buscadas o consultadas para identificar estudios. Especifique la fecha en la que se buscó o consultó por última vez cada fuente. | E11: TRUE | F11: TRUE | G11: FALSE | H11: FALSE | I11: FALSE | J11: =COUNTIF(E11:I11,(NOT(FALSE))) -> 2
A12: 3 Estrategia de búsqueda | B12: Estrategia de búsqueda | C12: 7 | D12: Presentar las estrategias de búsqueda completas para todas las bases de datos, registros y sitios web, incluidos los filtros y los límites utilizados. | E12: TRUE | F12: FALSE | G12: FALSE | H12: FALSE | I12: FALSE | J12: =COUNTIF(E12:I12,(NOT(FALSE))) -> 1
A13: 5 Selección de estudios | B13: Proceso de selección | C13: 8 | D13: Especifique los métodos utilizados para decidir si un estudio cumplía los criterios para la inclusión de la revisión, incluidos cuántos revisores examinaron cada registro y cada informe recuperado, si trabajaron de forma independiente y, si procede, los detalles de las herramientas de automatización utilizadas en el proceso. | E13: FALSE | F13: FALSE | G13: FALSE | H13: FALSE | I13: FALSE | J13: =COUNTIF(E13:I13,(NOT(FALSE))) -> 0
A14: 6 Extracción de datos | B14: Proceso de recopilación de datos | C14: 9 | D14: Especifique los métodos utilizados para recopilar los datos de los estudios, incluido el número de revisores que recopilaron datos de cada informe, si trabajaron de forma independiente, los procesos para obtener o confirmar datos de los investigadores del estudio y, si procede, los detalles de las herramientas de automatización utilizadas en el proceso. | E14: FALSE | F14: FALSE | G14: FALSE | H14: FALSE | I14: FALSE | J14: =COUNTIF(E14:I14,(NOT(FALSE))) -> 0
A15: 6 Extracción de datos | B15: Lista de datos | C15: 10a | D15: Enumerar y definir todos los desenlaces (outcomes) para los cuales se buscaron datos. Especifique si se buscaron todos los resultados admitidos por cada desenlace (outcome) en cada estudio (por ejemplo, para todas las medidas, puntos de tiempo, análisis) y, si no, los métodos utilizados para decidir qué resultados recopilar. | E15: FALSE | F15: FALSE | G15: FALSE | H15: FALSE | I15: FALSE | J15: =COUNTIF(E15:I15,(NOT(FALSE))) -> 0
A16: 8 Síntesis | C16: 10b | D16: Enumerar y definir todas las demás variables para las cuales se buscaron datos (por ejemplo, características de participante e intervención, fuentes de financiación). Describa cualquier asunción hecha sobre cualquier información que falte o no esté clara. | E16: FALSE | F16: FALSE | G16: FALSE | H16: FALSE | I16: FALSE | J16: =COUNTIF(E16:I16,(NOT(FALSE))) -> 0
A17: 7 Evaluación de calidad | B17: Estudio y valoración del riesgo de sesgo | C17: 11 | D17: Especifique los métodos utilizados para evaluar el riesgo de sesgo en los estudios incluidos, incluidos los detalles de las herramientas utilizadas, cuántos revisores evaluaron cada estudio y si trabajaron de forma independiente y, si procede, los detalles de las herramientas de automatización utilizadas en el proceso. | E17: FALSE | F17: FALSE | G17: FALSE | H17: FALSE | I17: FALSE | J17: =COUNTIF(E17:I17,(NOT(FALSE))) -> 0
A18: 7 Evaluación de calidad | B18: Medidas de efecto | C18: 12 | D18: Especifique para cada resultado como se midió el efecto (por ejemplo, riesgo relativo, diferencia de medias) utilizadas en la síntesis o presentación de resultados. | E18: FALSE | F18: FALSE | G18: FALSE | H18: FALSE | I18: FALSE | J18: =COUNTIF(E18:I18,(NOT(FALSE))) -> 0
A19: 8 Síntesis | B19: Métodos de síntesis | C19: 13a | D19: Describa los procesos utilizados para decidir qué estudios eran elegibles para cada síntesis. (por ejemplo, tabular las características de la intervención del estudio y comparar con los grupos planificados para cada síntesis (ítem #5)). | E19: FALSE | F19: FALSE | G19: FALSE | H19: FALSE | I19: FALSE | J19: =COUNTIF(E19:I19,(NOT(FALSE))) -> 0
A20: 8 Síntesis | C20: 13b | D20: Describir los métodos necesarios para preparar los datos para la presentación o síntesis, como el manejo de las estadísticas de resumen que faltan o las conversiones de datos. | E20: FALSE | F20: FALSE | G20: FALSE | H20: FALSE | I20: FALSE | J20: =COUNTIF(E20:I20,(NOT(FALSE))) -> 0
A21: 8 Síntesis | C21: 13c | D21: Describir cualquier método utilizado para tabular o mostrar visualmente los resultados de estudios individuales y síntesis. | E21: FALSE | F21: FALSE | G21: FALSE | H21: FALSE | I21: FALSE | J21: =COUNTIF(E21:I21,(NOT(FALSE))) -> 0
A22: 8 Síntesis | C22: 13d | D22: Describir los métodos utilizados para sintetizar resultados y proporcionar justificación para las opciones. Si se realizó un metanálisis, describa el modelo (s), el método(s) para identificar la presencia y el alcance de la heterogeneidad estadística y paquete(s) de software utilizados. | E22: FALSE | F22: FALSE | G22: FALSE | H22: FALSE | I22: FALSE | J22: =COUNTIF(E22:I22,(NOT(FALSE))) -> 0
A23: 8 Síntesis | C23: 13e | D23: Describa los métodos utilizados para explorar las posibles causas de la heterogeneidad entre los resultados del estudio (por ejemplo análisis de subgrupos, meta-regresión) | E23: FALSE | F23: FALSE | G23: FALSE | H23: FALSE | I23: FALSE | J23: =COUNTIF(E23:I23,(NOT(FALSE))) -> 0
A24: 8 Síntesis | C24: 13f | D24: Describir los análisis de sensibilidad realizados para evaluar la fortaleza de los resultados sintetizados. | E24: FALSE | F24: FALSE | G24: FALSE | H24: FALSE | I24: FALSE | J24: =COUNTIF(E24:I24,(NOT(FALSE))) -> 0
A25: 7 Evaluación de calidad | B25: Informar de la evaluación del sesgo | C25: 14 | D25: Describa cualquier método utilizado para evaluar el riesgo de sesgo debido a la falta de resultados en una síntesis (derivada de sesgos de notificación). | E25: FALSE | F25: FALSE | G25: FALSE | H25: FALSE | I25: FALSE | J25: =COUNTIF(E25:I25,(NOT(FALSE))) -> 0
A26: 7 Evaluación de calidad | B26: Evaluación de la certeza | C26: 15 | D26: Describa cualquier método utilizado para evaluar la certeza (o confianza) en el cuerpo de evidencia para un desenlace. | E26: FALSE | F26: FALSE | G26: FALSE | H26: FALSE | I26: FALSE | J26: =COUNTIF(E26:I26,(NOT(FALSE))) -> 0
C27: RESULTADOS | J27: X
A28: 8 Síntesis | B28: Selección de los estudios | C28: 16a | D28: Describa los resultados del proceso de búsqueda y selección, desde el número de registros identificados en la búsqueda hasta el número de estudios incluidos en la revisión, idealmente utilizando un diagrama de flujo (consulte la figura 1). | E28: FALSE | F28: FALSE | G28: FALSE | H28: FALSE | I28: FALSE | J28: =COUNTIF(E28:I28,(NOT(FALSE))) -> 0
A29: 8 Síntesis | C29: 16b | D29: Cite los estudios que parece que cumplieran muchos criterios de inclusión y explique por qué fueron excluidos. | E29: FALSE | F29: FALSE | G29: FALSE | H29: FALSE | I29: FALSE | J29: =COUNTIF(E29:I29,(NOT(FALSE))) -> 0
A30: 8 Síntesis | B30: Características del estudio | C30: 17 | D30: Cite cada estudio incluido y muestre sus características. | E30: FALSE | F30: FALSE | G30: FALSE | H30: FALSE | I30: FALSE | J30: =COUNTIF(E30:I30,(NOT(FALSE))) -> 0
A31: 7 Evaluación de calidad | B31: Riesgo de sesgo en los estudios | C31: 18 | D31: Presente la evaluación del riesgo de sesgo para cada estudio que se incluido en la revisión. | E31: FALSE | F31: FALSE | G31: FALSE | H31: FALSE | I31: FALSE | J31: =COUNTIF(E31:I31,(NOT(FALSE))) -> 0
A32: 8 Síntesis | B32: Resultados de estudios individuales | C32: 19 | D32: Para los resultados de cada estudio: a) estadísticas resumidas para cada grupo (cuando proceda) y b) una estimación de efectos y su precisión (por ejemplo, intervalo confianza/intervalo creíble), idealmente utilizando tablas o gráficas estructuradas. | E32: FALSE | F32: FALSE | G32: FALSE | H32: FALSE | I32: FALSE | J32: =COUNTIF(E32:I32,(NOT(FALSE))) -> 0
A33: 8 Síntesis | B33: Resultados de la síntesis | C33: 20a | D33: Para cada combinación o síntesis, resuma brevemente las características y el riesgo de sesgo entre los estudios. | E33: FALSE | F33: FALSE | G33: FALSE | H33: FALSE | I33: FALSE | J33: =COUNTIF(E33:I33,(NOT(FALSE))) -> 0
A34: 8 Síntesis | C34: 20b | D34: Presente los resultados de todas las combinaciones o síntesis estadísticas realizadas. Si se realizó un metanálisis, presente para cada uno un resumen de la estimación y su precisión (por ejemplo. confianza/intervalo creíble) y medidas estadísticas de heterogeneidad. Si compara grupos, describa la dirección del efecto. | E34: FALSE | F34: FALSE | G34: FALSE | H34: FALSE | I34: FALSE | J34: =COUNTIF(E34:I34,(NOT(FALSE))) -> 0
A35: 8 Síntesis | C35: 20c | D35: Presente resultados de toda la investigación de posibles causas de heterogeneidad entre los resultados del estudio. | E35: FALSE | F35: FALSE | G35: FALSE | H35: FALSE | I35: FALSE | J35: =COUNTIF(E35:I35,(NOT(FALSE))) -> 0
A36: 8 Síntesis | C36: 20d | D36: Presente los resultados de todos los análisis de sensibilidad realizados para evaluar la solidez de los resultados combinados. | E36: FALSE | F36: FALSE | G36: FALSE | H36: FALSE | I36: FALSE | J36: =COUNTIF(E36:I36,(NOT(FALSE))) -> 0
A37: 7 Evaluación de calidad | B37: Reportar sesgos | C37: 21 | D37: Evaluaciones de los riesgos de sesgo debido a la falta de resultados (derivados de sesgos de notificación) para cada combinación evaluada. | E37: FALSE | F37: FALSE | G37: FALSE | H37: FALSE | I37: FALSE | J37: =COUNTIF(E37:I37,(NOT(FALSE))) -> 0
A38: 7 Evaluación de calidad | B38: Certeza de la evidencia | C38: 22 | D38: Proporcione evaluaciones de certeza (o confianza) en la evidencia de cada resultado evaluado. | E38: FALSE | F38: FALSE | G38: FALSE | H38: FALSE | I38: FALSE | J38: =COUNTIF(E38:I38,(NOT(FALSE))) -> 0
C39: DISCUSI0N | J39: X
A40: 9 Redacción | B40: Discusión | C40: 23a | D40: Proporcionar una interpretación general de los resultados en el contexto de otras pruebas. | E40: FALSE | F40: FALSE | G40: FALSE | H40: FALSE | I40: FALSE | J40: =COUNTIF(E40:I40,(NOT(FALSE))) -> 0
A41: 9 Redacción | C41: 23b | D41: Discuta cualquier limitación de la evidencia incluida en el examen | E41: FALSE | F41: FALSE | G41: FALSE | H41: FALSE | I41: FALSE | J41: =COUNTIF(E41:I41,(NOT(FALSE))) -> 0
A42: 9 Redacción | C42: 23c | D42: Discutir las limitaciones de los procesos de revisión utilizados. | E42: FALSE | F42: FALSE | G42: FALSE | H42: FALSE | I42: FALSE | J42: =COUNTIF(E42:I42,(NOT(FALSE))) -> 0
A43: 9 Redacción | C43: 23d | D43: Discutir las implicaciones de los resultados para la práctica, la política y la investigación futura | E43: FALSE | F43: FALSE | G43: FALSE | H43: FALSE | I43: FALSE | J43: =COUNTIF(E43:I43,(NOT(FALSE))) -> 0
C44: MÁS INFORMACIÓN | J44: X
A45: 2 Protocolo | B45: Registro y protocolo | C45: 24a | D45: Proporcione información del registro de la revisión, incluido el nombre del registro y el número de registro, o indique que la revisión no se registró. | E45: TRUE | F45: FALSE | G45: TRUE | H45: FALSE | I45: FALSE | J45: =COUNTIF(E45:I45,(NOT(FALSE))) -> 2 | K45: registradp
A46: 2 Protocolo | B46: . | C46: 24b | D46: Indique dónde se puede acceder al protocolo de revisión o indique que no se ha preparado un protocolo. | E46: TRUE | F46: FALSE | G46: TRUE | H46: FALSE | I46: FALSE | J46: =COUNTIF(E46:I46,(NOT(FALSE))) -> 2
A47: 2 Protocolo | C47: 24c | D47: Describir y explicar cualquier cambio en la información proporcionada en el registro o protocolo. | E47: TRUE | F47: FALSE | G47: TRUE | H47: FALSE | I47: TRUE | J47: =COUNTIF(E47:I47,(NOT(FALSE))) -> 3
A48: 2 Protocolo | B48: Apoyo | C48: 25 | D48: Describa las fuentes de apoyo financiero o no financiero para su revisión, y el papel de los financiadores o patrocinadores en la revisión. | E48: TRUE | F48: FALSE | G48: TRUE | H48: FALSE | I48: FALSE | J48: =COUNTIF(E48:I48,(NOT(FALSE))) -> 2 | K48: NA
A49: 9 Redacción | B49: Conflicto de intereses competitivos | C49: 26 | D49: Declarar cualquier conflicto de interés de los autores de las revisiones. | E49: FALSE | F49: FALSE | G49: FALSE | H49: FALSE | I49: FALSE | J49: =COUNTIF(E49:I49,(NOT(FALSE))) -> 0
A50: 10 Revisión final | B50: Disponibilidad de datos, código y otros materiales | C50: 27 | D50: Informe cuáles de las siguientes opciones están disponibles públicamente y dónde se pueden encontrar: formularios y plantillas de recopilación de datos; datos extraídos de los estudios incluidos; datos utilizados para todos los análisis; código analítico; cualquier otro material utilizado en la revisión. | E50: FALSE | F50: FALSE | G50: FALSE | H50: FALSE | I50: FALSE | J50: =COUNTIF(E50:I50,(NOT(FALSE))) -> 0
C51: Titulo | D51: .Tabla 2.1.- Lista de verificación PRISMA 2020 para resúmenes* | J51: X
A52: 10 Revisión final | B52: Titulo | C52: 1 | D52: Identifique el informe como una revisión sistemática | E52: FALSE | F52: FALSE | G52: FALSE | H52: FALSE | I52: FALSE | J52: =COUNTIF(E52:I52,(NOT(FALSE))) -> 0
C53: Información básica | J53: X
A54: 9 Redacción | B54: Objetivos | C54: 2 | D54: Proporcione una declaración explícita de los principales objetivos(s) o pregunta(s) que se plantea la revisión. | E54: FALSE | F54: FALSE | G54: FALSE | H54: FALSE | I54: FALSE | J54: =COUNTIF(E54:I54,(NOT(FALSE))) -> 0 | K54: RESUMEN
C55: Métodos | J55: X
A56: 9 Redacción | B56: Criterios de elegibilidad | C56: 3 | D56: Especifique los criterios de inclusión y exclusión de la revisión | E56: FALSE | F56: FALSE | G56: FALSE | H56: FALSE | I56: FALSE | J56: =COUNTIF(E56:I56,(NOT(FALSE))) -> 0 | K56: RESUMEN
A57: 4 Búsqueda bibliográfica | B57: Fuentes de información | C57: 4 | D57: Especifique las fuentes de información (por ejemplo, bases de datos, registros) utilizadas para identificar estudios y la fecha en que se buscó cada una por última vez. | E57: TRUE | F57: TRUE | G57: FALSE | H57: FALSE | I57: FALSE | J57: =COUNTIF(E57:I57,(NOT(FALSE))) -> 2
A58: 7 Evaluación de calidad | B58: Riesgo de sesgo | C58: 5 | D58: Especifique los métodos utilizados para evaluar el riesgo de sesgo de los estudios incluidos. | E58: FALSE | F58: FALSE | G58: FALSE | H58: FALSE | I58: FALSE | J58: =COUNTIF(E58:I58,(NOT(FALSE))) -> 0
A59: 8 Síntesis | B59: Síntesis de resultados | C59: 6 | D59: Especifique los métodos utilizados para presentar y sintetizar resultados. | E59: FALSE | F59: FALSE | G59: FALSE | H59: FALSE | I59: FALSE | J59: =COUNTIF(E59:I59,(NOT(FALSE))) -> 0
C60: Resultados | J60: X
A61: 8 Síntesis | B61: Estudios incluidos | C61: 7 | D61: Dar el número total de estudios y participantes incluidos y resumir las características relevantes de los estudios | E61: FALSE | F61: FALSE | G61: FALSE | H61: FALSE | I61: FALSE | J61: =COUNTIF(E61:I61,(NOT(FALSE))) -> 0
A62: 8 Síntesis | B62: Síntesis de los resultados | C62: 8 | D62: Presentar resultados para los desenlaces (outcomes) principales, indicando preferiblemente el número de estudios incluidos y participantes para cada uno. Si se hizo un metanálisis, informe de la estimación resumida y el intervalo de confianza / creíble. Si se comparan grupos, indique la dirección del efecto (es decir, que grupo es favorecido). | E62: FALSE | F62: FALSE | G62: FALSE | H62: FALSE | I62: FALSE | J62: =COUNTIF(E62:I62,(NOT(FALSE))) -> 0
C63: Discusión | J63: X
A64: 9 Redacción | B64: Limitaciones de la evidencia | C64: 9 | D64: Proporcione un breve resumen de las limitaciones de las pruebas incluidas en la revisión (por ejemplo, riesgo de sesgo, inconsistencia e imprecisión del estudio). | E64: FALSE | F64: FALSE | G64: FALSE | H64: FALSE | I64: FALSE | J64: =COUNTIF(E64:I64,(NOT(FALSE))) -> 0
A65: 9 Redacción | B65: Interpretación | C65: 10 | D65: Proporcione una interpretación general de los resultados y de las implicaciones importantes | E65: FALSE | F65: FALSE | G65: FALSE | H65: FALSE | I65: FALSE | J65: =COUNTIF(E65:I65,(NOT(FALSE))) -> 0
C66: FUENTES DE INFORMACIÓN Y MÉTODOS | D66: .Tabla 1 Lista de verificación de PRISMA-S. Una versión descargable de la lista de comprobación está disponible en la web de PRISMA | J66: X
A67: 3 Estrategia de búsqueda | B67: Nombre de la base de datos | C67: 1 | D67: Nombra cada base de datos individual buscada, indicando la plataforma de cada una. | E67: TRUE | F67: FALSE | G67: FALSE | H67: FALSE | I67: FALSE | J67: =COUNTIF(E67:I67,(NOT(FALSE))) -> 1
A68: 3 Estrategia de búsqueda | B68: Búsqueda multibase de datos | C68: 2 | D68: Si se buscaron bases de datos simultáneamente en una sola plataforma, se indica el nombre de la plataforma, listando todas las bases de datos buscadas. | E68: TRUE | F68: FALSE | G68: FALSE | H68: FALSE | I68: FALSE | J68: =COUNTIF(E68:I68,(NOT(FALSE))) -> 1
A69: 3 Estrategia de búsqueda | B69: Registros de estudios | C69: 3 | D69: Enumera cualquier registro de estudios que hayas buscado. | E69: TRUE | F69: FALSE | G69: FALSE | H69: FALSE | I69: FALSE | J69: =COUNTIF(E69:I69,(NOT(FALSE))) -> 1 | K69: REVISTAS Y PREPRINTS
A70: 3 Estrategia de búsqueda | B70: Recursos online y navegación | C70: 4 | D70: Describe cualquier fuente en línea o impresa que se haya buscado o navegado intencionadamente (por ejemplo, índice, actas impresas de conferencias, sitios web) y cómo se hizo esto. | E70: TRUE | F70: FALSE | G70: FALSE | H70: FALSE | I70: FALSE | J70: =COUNTIF(E70:I70,(NOT(FALSE))) -> 1 | K70: CITAR RECURSOS
A71: 3 Estrategia de búsqueda | B71: Búsqueda de citas | C71: 5 | D71: Indica si se han examinado referencias citadas o referencias citantes, y describe cualquier método utilizado para localizar referencias citadas/citantes (por ejemplo, navegar por listas de referencias, usar un índice de citas, configurar alertas por correo electrónico para referencias que citen estudios incluidos). | E71: TRUE | F71: FALSE | G71: FALSE | H71: FALSE | I71: FALSE | J71: =COUNTIF(E71:I71,(NOT(FALSE))) -> 1 | K71: COMPARAR EL QUE ESTA CON EL QUE HICE…
A72: 3 Estrategia de búsqueda | B72: Contactos | C72: 6 | D72: Indica si se solicitaron estudios o datos adicionales contactando a autores, expertos, fabricantes u otros. | E72: TRUE | F72: FALSE | G72: FALSE | H72: FALSE | I72: FALSE | J72: =COUNTIF(E72:I72,(NOT(FALSE))) -> 1 | K72: BUSCAR A MAX JONES
A73: 3 Estrategia de búsqueda | B73: Otros métodos | C73: 7 | D73: Describe cualquier fuente adicional de información o método de búsqueda utilizado. | E73: TRUE | F73: FALSE | G73: FALSE | H73: FALSE | I73: FALSE | J73: =COUNTIF(E73:I73,(NOT(FALSE))) -> 1 | K73: NA?
A74: 3 Estrategia de búsqueda | C74: ESTRATEGIAS DE BÚSQUEDA | J74: X
A75: 3 Estrategia de búsqueda | B75: Estrategias de búsqueda completas | C75: 8 | D75: Incluye las estrategias de búsqueda para cada base de datos y fuente de información, copiadas y pegadas exactamente tal como se ejecuta. | E75: TRUE | F75: FALSE | G75: FALSE | H75: FALSE | I75: FALSE | J75: =COUNTIF(E75:I75,(NOT(FALSE))) -> 1
A76: 3 Estrategia de búsqueda | B76: Límites y restricciones | C76: 9 | D76: Especificar que no se han utilizado límites, o describir cualquier límite o restricción aplicado a una búsqueda (por ejemplo, fecha o periodo de tiempo, idioma, diseño de estudio) y proporcionar justificación para su uso. | E76: TRUE | F76: FALSE | G76: FALSE | H76: FALSE | I76: FALSE | J76: =COUNTIF(E76:I76,(NOT(FALSE))) -> 1
A77: 3 Estrategia de búsqueda | B77: Filtros de búsqueda | C77: 10 | D77: Indica si se usaron filtros de búsqueda publicados (tal como fueron diseñados originalmente o modificados) y, en caso afirmativo, cita el/los filtro o filtros utilizados. | E77: TRUE | F77: FALSE | G77: FALSE | H77: FALSE | I77: FALSE | J77: =COUNTIF(E77:I77,(NOT(FALSE))) -> 1 | K77: NO
A78: 3 Estrategia de búsqueda | B78: Trabajos previos | C78: 11 | D78: Indicar cuándo se han adaptado o reutilizado estrategias de búsqueda de otras revisiones bibliográficas para una parte sustantiva o para toda la búsqueda, citando la(s) revisión(es) previa(s). | E78: TRUE | F78: FALSE | G78: TRUE | H78: FALSE | I78: FALSE | J78: =COUNTIF(E78:I78,(NOT(FALSE))) -> 2
A79: 3 Estrategia de búsqueda | B79: Actualizaciones | C79: 12 | D79: Informa de los métodos utilizados para actualizar la(s) búsqueda(s) (por ejemplo, volver a ejecutar búsquedas, alertas por correo electrónico). | E79: TRUE | F79: FALSE | G79: FALSE | H79: FALSE | I79: FALSE | J79: =COUNTIF(E79:I79,(NOT(FALSE))) -> 1 | K79: ESTABLECER EN FECHAS
A80: 3 Estrategia de búsqueda | B80: Fechas de las búsquedas | C80: 13 | D80: Para cada estrategia de búsqueda, proporciona la fecha en que se realizó la última búsqueda. | E80: TRUE | F80: FALSE | G80: FALSE | H80: FALSE | I80: FALSE | J80: =COUNTIF(E80:I80,(NOT(FALSE))) -> 1 | K80: REALIZARLAS
C81: REVISIÓN POR PARES | J81: X
A82: 3 Estrategia de búsqueda | B82: Revisión por pares | C82: 14 | D82: Describe cualquier proceso de revisión por pares de búsqueda. | E82: TRUE | F82: FALSE | G82: TRUE | H82: FALSE | I82: FALSE | J82: =COUNTIF(E82:I82,(NOT(FALSE))) -> 2 | K82: SE HICIERON DOS BUSQUEDAS CON RESULTADOS SIMILARES
C83: DISCOS DE GESTIÓN | J83: X
A84: 3 Estrategia de búsqueda | B84: Récords totales | C84: 15 | D84: Documenta el número total de registros identificados en cada base de datos y otras fuentes de información. | E84: TRUE | F84: FALSE | G84: FALSE | H84: FALSE | I84: FALSE | J84: =COUNTIF(E84:I84,(NOT(FALSE))) -> 1 | K84: REALIZAR DIAGRAMA PRISMA
A85: 3 Estrategia de búsqueda | B85: Deduplicación | C85: 16 | D85: Describe los procesos y cualquier software utilizado para deduplicar registros de múltiples búsquedas en bases de datos y otras fuentes de información. | E85: TRUE | F85: FALSE | G85: FALSE | H85: FALSE | I85: FALSE | J85: =COUNTIF(E85:I85,(NOT(FALSE))) -> 1 | K85: USAR EXCEL O ZOTERO
C86: PRESS | D86: .Tabla3. Lista de verificación basada en la evidencia de la Guía PRESS 2015 | J86: X
A87: 3 Estrategia de búsqueda | B87: Traducción de la pregunta de investigación | C87: 1 | D87: ¿La estrategia de búsqueda coincide con la pregunta de investigación/PICO? | E87: TRUE | F87: FALSE | G87: FALSE | H87: FALSE | I87: FALSE | J87: =COUNTIF(E87:I87,(NOT(FALSE))) -> 1
A88: 3 Estrategia de búsqueda | D88: ¿Son claros los conceptos de búsqueda? | E88: TRUE | F88: FALSE | G88: FALSE | H88: FALSE | I88: FALSE | J88: =COUNTIF(E88:I88,(NOT(FALSE))) -> 1
A89: 3 Estrategia de búsqueda | D89: ¿Hay demasiados o muy pocos elementos PICO incluidos? | E89: TRUE | F89: FALSE | G89: FALSE | H89: FALSE | I89: FALSE | J89: =COUNTIF(E89:I89,(NOT(FALSE))) -> 1
A90: 3 Estrategia de búsqueda | D90: ¿Son los conceptos de búsqueda demasiado limitados o demasiado amplios? | E90: TRUE | F90: FALSE | G90: FALSE | H90: FALSE | I90: FALSE | J90: =COUNTIF(E90:I90,(NOT(FALSE))) -> 1
A91: 3 Estrategia de búsqueda | D91: ¿La búsqueda recupera demasiados o muy pocos registros? (Por favor, muestra el número de visitas por línea.) | E91: TRUE | F91: FALSE | G91: FALSE | H91: FALSE | I91: FALSE | J91: =COUNTIF(E91:I91,(NOT(FALSE))) -> 1
A92: 3 Estrategia de búsqueda | D92: ¿Se explican las estrategias no convencionales o complejas? | E92: TRUE | F92: FALSE | G92: FALSE | H92: FALSE | I92: FALSE | J92: =COUNTIF(E92:I92,(NOT(FALSE))) -> 1 | K92: DOS RAMAS
A93: 3 Estrategia de búsqueda | B93: Operadores booleanos y de proximidad (estos varían según el servicio de búsqueda) | C93: 2 | D93: ¿Se usan correctamente los operadores booleanos o de proximidad? | E93: TRUE | F93: FALSE | G93: FALSE | H93: FALSE | I93: FALSE | J93: =COUNTIF(E93:I93,(NOT(FALSE))) -> 1
A94: 3 Estrategia de búsqueda | D94: ¿Es apropiado y efectivo el uso del anidamiento con corchetes para la búsqueda? | E94: TRUE | F94: FALSE | G94: FALSE | H94: FALSE | I94: FALSE | J94: =COUNTIF(E94:I94,(NOT(FALSE))) -> 1
A95: 3 Estrategia de búsqueda | D95: Si se usa NO (NO se usa), ¿es probable que esto resulte en alguna exclusión no deseada? | E95: TRUE | F95: FALSE | G95: FALSE | H95: FALSE | I95: FALSE | J95: =COUNTIF(E95:I95,(NOT(FALSE))) -> 1 | K95: SI SE USA PARA ELIMINAR TERMINOS QUE NO DEBEN INCLUIRSE EN TITULO
A96: 3 Estrategia de búsqueda | D96: ¿Se podría mejorar la precisión usando operadores de proximidad (por ejemplo, adyacente, cerca, dentro) o búsqueda por frases en lugar de AND? | E96: TRUE | F96: FALSE | G96: FALSE | H96: FALSE | I96: FALSE | J96: =COUNTIF(E96:I96,(NOT(FALSE))) -> 1 | K96: SI
A97: 3 Estrategia de búsqueda | D97: ¿Es adecuada la anchura de los operadores de proximidad (por ejemplo, ¿podría adj5 captar más variantes que adj2)? | E97: TRUE | F97: FALSE | G97: FALSE | H97: FALSE | I97: FALSE | J97: =COUNTIF(E97:I97,(NOT(FALSE))) -> 1 | K97: NA
A98: 3 Estrategia de búsqueda | B98: Encabezados de materia (específicos de la base de datos) | C98: 3 | D98: ¿Son relevantes los encabezados de los temas? | E98: TRUE | F98: FALSE | G98: FALSE | H98: FALSE | I98: FALSE | J98: =COUNTIF(E98:I98,(NOT(FALSE))) -> 1
A99: 3 Estrategia de búsqueda | D99: ¿Faltan encabezados relevantes de materias? Por ejemplo, ¿términos de índice anteriores? | E99: TRUE | F99: FALSE | G99: FALSE | H99: FALSE | I99: FALSE | J99: =COUNTIF(E99:I99,(NOT(FALSE))) -> 1
A100: 3 Estrategia de búsqueda | D100: ¿Hay algún encabezado de materia demasiado amplio o demasiado limitado? | E100: TRUE | F100: FALSE | G100: FALSE | H100: FALSE | I100: FALSE | J100: =COUNTIF(E100:I100,(NOT(FALSE))) -> 1 | K100: NAA
...

Sheet Hoja3
F7: ESTADO | G7: NO EMPEZADO | H7: EN PROCESO | I7: FINALIZADO | J7: NOTAS ADICIONALES
C9: Sección/Tema | D9: Ítem | E9: Elemento de la lista de verificación | F9: ESTADO | G9: fecha
C10: PROTOCOLO | D10: 0 | E10: protocol 2.0 | F10: FINALIZADO | G10: 46266
C11: TÍTULO | D11: 1 | E11: Identificar el documento como revisión sistemática, metaanálisis o ambos. | F11: EN PROCESO | G11: 46325
C12: RESUMEN | D12: 2 | E12: Presentar un resumen estructurado que incluya antecedentes, objetivos, fuentes, criterios, métodos, resultados, limitaciones y conclusiones. | F12: NO EMPEZADO | G12: 46325
C13: INTRODUCCIÓN | D13: 3 a 4 | E13: Explicar la justificación en el contexto del conocimiento actual definir los objetivos según PICOS: población, intervención, comparador, desenlace y diseño. | F13: EN PROCESO | G13: 46280
C14: MÉTODOS | D14: 5 a 16 | E14: Describir protocolo y registro, criterios de elegibilidad, fuentes de información, estrategia de búsqueda, selección de estudios, recolección y elementos de datos, evaluación del riesgo de sesgo, medidas de resumen, síntesis de resultados y análisis adicionales. | F14: EN PROCESO | G14: 46295
C15: RESULTADOS | D15: 17 a 23 | E15: Presentar la selección y características de los estudios, el riesgo de sesgo, los resultados individuales, la síntesis, los sesgos de notificación y los análisis adicionales. | F15: EN PROCESO | G15: 46310
C16: DISCUSIÓN | D16: 24 a 26 | E16: Resumir la evidencia, discutir las limitaciones y presentar las conclusiones. | F16: NO EMPEZADO | G16: 46325
C17: FINANCIAMIENTO | D17: 27 | E17: Indicar las fuentes de financiamiento y el papel de los financiadores.
C21: FECHA TENTATIVA DE REVISION | D21: FASE | E21: ACTIVIDADES PARA REVISAR CON CHECKLIST | F21: ESTADO | G21: PROGRESO | H21: Columna1
C22: 46235 | D22: 1 Planeación | E22: Definir pregunta de investigación, objetivos, criterios de inclusión/exclusión y equipo de trabajo. | F22: TERMINADO | G22: =COUNTIFS(Checklist!J:J,"<>0",Checklist!A:A,Tabla1[[#This Row],[FASE]],Checklist!J:J,"0") -> 0
C23: 46245 | D23: 2 Protocolo | E23: Redactar el protocolo y registrar la revisión si aplica. | F23: TERMINADO
C24: 46266 | D24: 3 Estrategia de búsqueda | E24: Diseñar ecuaciones de búsqueda, seleccionar bases de datos y probar la estrategia. | F24: TERMINADO
C25: 46268 | D25: 4 Búsqueda bibliográfica | E25: Ejecutar búsquedas en bases de datos y otras fuentes, descargar resultados y eliminar duplicados. | F25: EN PROCESO
C26: 46280 | D26: 5 Selección de estudios | E26: Revisar títulos/resúmenes y luego textos completos según criterios de elegibilidad.
C27: 46295 | D27: 6 Extracción de datos | E27: Diseñar formulario, extraer datos y verificar consistencia entre revisores.
C28: 46310 | D28: 7 Evaluación de calidad | E28: Valorar riesgo de sesgo o calidad metodológica de los estudios incluidos.
C29: 46325 | D29: 8 Síntesis | E29: Realizar síntesis narrativa Y meta-análisis, según corresponda.
C30: 46341 | D30: 9 Redacción | E30: Escribir resultados, discusión, conclusiones y preparar figuras/tablas.
C31: 46356 | D31: 10 Revisión final | E31: Correcciones de coautores, ajuste al formato de revista y envío.

Sheet SeccinTema-tem-Checklistitem.
E1: Miss Andrea Estefania Aranda Rosas | F1: Mr Leandro Jesus Lozano Garcia | G1: Professor Miguel Angel Trejo-Rodriguez | H1: Professor Erik Gonzalez-Ballesteros | I1: Dr Sandra Martinez Robles
E2: AUTOR, REVISOR | F2: AUTOR, REVISOR | G2: ASESOR, AUTOR | H2: ASESOR | I2: ASESOR
A3: fecha | B3: Sección/Tema | C3: Ítem | D3: Elemento de la lista de verificación | E3: AAR | F3: LLG | G3: MTR | H3: EGB | I3: SMR
A4: 46266 | B4: PROTOCOLO | C4: 0 | D4: protocol 2.0 | E4: TRUE | F4: FALSE | G4: TRUE | H4: FALSE | I4: TRUE
A5: 46325 | B5: TÍTULO | C5: 1 | D5: Identificar el documento como revisión sistemática, metaanálisis o ambos. | E5: FALSE | F5: FALSE | G5: TRUE | H5: TRUE | I5: TRUE
A6: 46325 | B6: RESUMEN | C6: 2 | D6: Presentar un resumen estructurado que incluya antecedentes, objetivos, fuentes, criterios, métodos, resultados, limitaciones y conclusiones. | E6: FALSE | F6: FALSE | G6: FALSE | H6: FALSE | I6: FALSE
A7: 46280 | B7: INTRODUCCIÓN | C7: 3 a 4 | D7: Explicar la justificación en el contexto del conocimiento actual definir los objetivos según PICOS: población, intervención, comparador, desenlace y diseño. | E7: FALSE | F7: FALSE | G7: FALSE | H7: FALSE | I7: FALSE
A8: 46295 | B8: MÉTODOS | C8: 5 a 16 | D8: Describir protocolo y registro, criterios de elegibilidad, fuentes de información, estrategia de búsqueda, selección de estudios, recolección y elementos de datos, evaluación del riesgo de sesgo, medidas de resumen, síntesis de resultados y análisis adicionales. | E8: FALSE | F8: FALSE | G8: FALSE | H8: FALSE | I8: FALSE
A9: 46310 | B9: RESULTADOS | C9: 17 a 23 | D9: Presentar la selección y características de los estudios, el riesgo de sesgo, los resultados individuales, la síntesis, los sesgos de notificación y los análisis adicionales. | E9: FALSE | F9: FALSE | G9: FALSE | H9: FALSE | I9: FALSE
A10: 46325 | B10: DISCUSIÓN | C10: 24 a 26 | D10: Resumir la evidencia, discutir las limitaciones y presentar las conclusiones. | E10: FALSE | F10: FALSE | G10: FALSE | H10: FALSE | I10: FALSE
B11: FINANCIAMIENTO | C11: 27 | D11: Indicar las fuentes de financiamiento y el papel de los financiadores. | E11: FALSE | F11: FALSE | G11: FALSE | H11: FALSE | I11: FALSE
A16: Fase | B16: Duración estimada | D16: Actividades | E16: AAR | F16: LLG | G16: MTR | H16: EGB | I16: SMR
A17: 1. Planeación | B17: Semanas 1–2 | D17: Definir pregunta de investigación, objetivos, criterios de inclusión/exclusión y equipo de trabajo. | E17: TRUE | F17: TRUE | G17: TRUE | H17: TRUE | I17: TRUE
A18: 2. Protocolo | B18: Semanas 3–4 | D18: Redactar el protocolo y registrar la revisión si aplica. | E18: TRUE | F18: FALSE | G18: TRUE | H18: FALSE | I18: FALSE
A19: 3. Estrategia de búsqueda | B19: Semanas 5–6 | D19: Diseñar ecuaciones de búsqueda, seleccionar bases de datos y probar la estrategia. | E19: TRUE | F19: FALSE | G19: TRUE | H19: FALSE | I19: FALSE
A20: 4. Búsqueda bibliográfica | B20: Semanas 7–8 | D20: Ejecutar búsquedas en bases de datos y otras fuentes, descargar resultados y eliminar duplicados. | E20: TRUE | F20: FALSE | G20: TRUE | H20: FALSE | I20: FALSE
A21: 5. Selección de estudios | B21: Semanas 9–12 | D21: Revisar títulos/resúmenes y luego textos completos según criterios de elegibilidad. | E21: FALSE | F21: FALSE | G21: FALSE | H21: FALSE | I21: FALSE
A22: 6. Extracción de datos | B22: Semanas 13–16 | D22: Diseñar formulario, extraer datos y verificar consistencia entre revisores. | E22: TRUE | F22: FALSE | G22: FALSE | H22: FALSE | I22: FALSE
A23: 7. Evaluación de calidad | B23: Semanas 15–17 | D23: Valorar riesgo de sesgo o calidad metodológica de los estudios incluidos. | E23: FALSE | F23: FALSE | G23: FALSE | H23: FALSE | I23: FALSE
A24: 8. Síntesis | B24: Semanas 18–20 | D24: Realizar síntesis narrativa o meta-análisis, según corresponda. | E24: FALSE | F24: FALSE | G24: FALSE | H24: FALSE | I24: FALSE
A25: 9. Redacción | B25: Semanas 21–24 | D25: Escribir resultados, discusión, conclusiones y preparar figuras/tablas. | E25: FALSE | F25: FALSE | G25: FALSE | H25: FALSE | I25: FALSE
A26: 10. Revisión final | B26: Semanas 25–26 | D26: Correcciones de coautores, ajuste al formato de revista y envío. | E26: FALSE | F26: FALSE | G26: FALSE | H26: FALSE | I26: FALSE
